{"cameraMode":{"drawMode":0,"name":"Shaded","section":"Shading Mode"},"sceneLighting":true,"audioPlay":false,"sceneViewState":{"m_AlwaysRefresh":false,"showFog":true,"showSkybox":true,"showFlares":true,"showImageEffects":true,"showParticleSystems":true,"showVisualEffectGraphs":true,"m_FxEnabled":true},"in2DMode":false,"pivot":{"x":2.7838103771209719,"y":0.5933191776275635,"z":-6.7877044677734379},"rotation":{"x":-0.16536374390125276,"y":-0.7610301971435547,"z":0.21333527565002442,"w":-0.5898997783660889},"size":2.086388111114502,"orthographic":false}